bumbo/__init__.py
bumbo/api.py
bumbo/middleware.py
bumbo/response.py
bumbo_roman_yank-0.0.1.dist-info/METADATA
bumbo_roman_yank-0.0.1.dist-info/WHEEL
bumbo_roman_yank-0.0.1.dist-info/top_level.txt
bumbo_roman_yank-0.0.1.dist-info/RECORD
