Metadata-Version: 2.1
Name: bumbo_roman_yank
Version: 0.0.1
Summary: Bumbo Python Web Framework built for learning purposes.
Author: 
Author-email: 
License: MIT
Classifier: Programming Language :: Python :: 3.6
Requires-Python: >=3.6.0
Requires-Dist: Jinja2 ==2.10.3
Requires-Dist: parse ==1.12.1
Requires-Dist: requests ==2.22.0
Requires-Dist: requests-wsgi-adapter ==0.4.1
Requires-Dist: WebOb ==1.8.5
Requires-Dist: whitenoise ==4.1.4
